Metadata-Version: 2.1
Name: xalign
Version: 0.1.74
Summary: Alignment in a python wrapper.
Home-page: https://github.com/maayanlab/xalign
Author: Alexander Lachmann
Author-email: alexander.lachmann@mssm.edu
Classifier: Programming Language :: Python :: 3
Classifier: License :: OSI Approved :: Apache Software License
Classifier: Operating System :: OS Independent
Requires-Python: >=3.6
License-File: LICENSE
